xrp/__init__.py
xrp/py.typed
xrp/version.py
xrp/extension/__init__.py
xrp/extension/main.py
xrp/extension/lib/libhalsim_xrp.dylib
xrp/src/main.cpp
xrp/_init__xrp.py
xrp/_xrp.cpython-311-darwin.so
xrp/_xrp.pyi
xrp/xrp.pc
xrp/trampolines/frc__XRPGyro.hpp
xrp/trampolines/frc__XRPMotor.hpp
xrp/trampolines/frc__XRPOnBoardIO.hpp
xrp/trampolines/frc__XRPRangefinder.hpp
xrp/trampolines/frc__XRPReflectanceSensor.hpp
xrp/trampolines/frc__XRPServo.hpp
robotpy_xrp-2025.3.2.3.dist-info/METADATA
robotpy_xrp-2025.3.2.3.dist-info/WHEEL
robotpy_xrp-2025.3.2.3.dist-info/entry_points.txt
robotpy_xrp-2025.3.2.3.dist-info/RECORD
