Metadata-Version: 2.4
Name: robotpy-xrp
Version: 2025.3.2.3
Summary: Binary wrapper for WPILib XRP Vendor library
Author-email: RobotPy Development Team <robotpy@googlegroups.com>
License-Expression: BSD-3-Clause
Requires-Dist: robotpy-native-xrp==2025.3.2
Requires-Dist: wpilib==2025.3.2.3
